[
  {
    "state": "Alabama",
    "2016obesrate": "35.70%",
    "2015obesrate": "35.60%",
    "2014obesrate": "33.50%",
    "2013obesrate": "32.40%",
    "2012obesrate": "33.00%"
  },
  {
    "state": "Alaska",
    "2016obesrate": "31.40%",
    "2015obesrate": "29.80%",
    "2014obesrate": "29.70%",
    "2013obesrate": "28.40%",
    "2012obesrate": "25.70%"
  },
  {
    "state": "Arizona",
    "2016obesrate": "29.00%",
    "2015obesrate": "28.40%",
    "2014obesrate": "28.90%",
    "2013obesrate": "26.80%",
    "2012obesrate": "26.00%"
  },
  {
    "state": "Arkansas",
    "2016obesrate": "35.70%",
    "2015obesrate": "34.50%",
    "2014obesrate": "35.90%",
    "2013obesrate": "34.60%",
    "2012obesrate": "34.50%"
  },
  {
    "state": "California",
    "2016obesrate": "25.00%",
    "2015obesrate": "24.20%",
    "2014obesrate": "24.70%",
    "2013obesrate": "24.10%",
    "2012obesrate": "25.00%"
  },
  {
    "state": "Colorado",
    "2016obesrate": "22.30%",
    "2015obesrate": "20.20%",
    "2014obesrate": "21.30%",
    "2013obesrate": "21.30%",
    "2012obesrate": "20.50%"
  },
  {
    "state": "Connectlcut",
    "2016obesrate": "26.00%",
    "2015obesrate": "25.30%",
    "2014obesrate": "26.30%",
    "2013obesrate": "25.00%",
    "2012obesrate": "25.60%"
  },
  {
    "state": "Delaware",
    "2016obesrate": "30.70%",
    "2015obesrate": "29.70%",
    "2014obesrate": "30.70%",
    "2013obesrate": "31.10%",
    "2012obesrate": "26.90%"
  },
  {
    "state": "District of Columbia",
    "2016obesrate": "22.60%",
    "2015obesrate": "22.10%",
    "2014obesrate": "21.70%",
    "2013obesrate": "22.90%",
    "2012obesrate": "21.90%"
  },
  {
    "state": "Florida",
    "2016obesrate": "27.40%",
    "2015obesrate": "26.80%",
    "2014obesrate": "26.20%",
    "2013obesrate": "26.40%",
    "2012obesrate": "25.20%"
  },
  {
    "state": "Georgia",
    "2016obesrate": "31.40%",
    "2015obesrate": "30.70%",
    "2014obesrate": "30.50%",
    "2013obesrate": "30.30%",
    "2012obesrate": "29.10%"
  },
  {
    "state": "Hawaii",
    "2016obesrate": "23.80%",
    "2015obesrate": "22.70%",
    "2014obesrate": "22.10%",
    "2013obesrate": "21.80%",
    "2012obesrate": "23.60%"
  },
  {
    "state": "Idaho",
    "2016obesrate": "27.40%",
    "2015obesrate": "28.60%",
    "2014obesrate": "28.90%",
    "2013obesrate": "29.60%",
    "2012obesrate": "26.80%"
  },
  {
    "state": "Illinois",
    "2016obesrate": "31.60%",
    "2015obesrate": "30.80%",
    "2014obesrate": "29.30%",
    "2013obesrate": "29.40%",
    "2012obesrate": "28.10%"
  },
  {
    "state": "Indiana",
    "2016obesrate": "32.50%",
    "2015obesrate": "32.80%",
    "2014obesrate": "32.70%",
    "2013obesrate": "31.80%",
    "2012obesrate": "31.40%"
  },
  {
    "state": "Iowa",
    "2016obesrate": "32.00%",
    "2015obesrate": "32.10%",
    "2014obesrate": "30.90%",
    "2013obesrate": "31.30%",
    "2012obesrate": "30.40%"
  },
  {
    "state": "Kansas",
    "2016obesrate": "31.20%",
    "2015obesrate": "34.20%",
    "2014obesrate": "31.30%",
    "2013obesrate": "30.00%",
    "2012obesrate": "29.90%"
  },
  {
    "state": "Kentucky",
    "2016obesrate": "34.20%",
    "2015obesrate": "34.60%",
    "2014obesrate": "31.60%",
    "2013obesrate": "33.20%",
    "2012obesrate": "31.30%"
  },
  {
    "state": "Louisiana",
    "2016obesrate": "35.50%",
    "2015obesrate": "36.20%",
    "2014obesrate": "34.90%",
    "2013obesrate": "33.10%",
    "2012obesrate": "34.70%"
  },
  {
    "state": "Maine",
    "2016obesrate": "29.90%",
    "2015obesrate": "30.00%",
    "2014obesrate": "28.20%",
    "2013obesrate": "28.90%",
    "2012obesrate": "28.40%"
  },
  {
    "state": "Maryland",
    "2016obesrate": "29.90%",
    "2015obesrate": "28.90%",
    "2014obesrate": "29.60%",
    "2013obesrate": "28.30%",
    "2012obesrate": "27.60%"
  },
  {
    "state": "Massachusetts",
    "2016obesrate": "23.60%",
    "2015obesrate": "24.30%",
    "2014obesrate": "23.30%",
    "2013obesrate": "23.60%",
    "2012obesrate": "22.90%"
  },
  {
    "state": "Michigan",
    "2016obesrate": "32.50%",
    "2015obesrate": "31.20%",
    "2014obesrate": "30.70%",
    "2013obesrate": "31.50%",
    "2012obesrate": "31.10%"
  },
  {
    "state": "Minnesota",
    "2016obesrate": "27.80%",
    "2015obesrate": "26.10%",
    "2014obesrate": "27.60%",
    "2013obesrate": "25.50%",
    "2012obesrate": "25.70%"
  },
  {
    "state": "Mississippi",
    "2016obesrate": "37.30%",
    "2015obesrate": "35.60%",
    "2014obesrate": "35.50%",
    "2013obesrate": "35.10%",
    "2012obesrate": "34.60%"
  },
  {
    "state": "Missouri",
    "2016obesrate": "31.70%",
    "2015obesrate": "32.40%",
    "2014obesrate": "30.20%",
    "2013obesrate": "30.40%",
    "2012obesrate": "29.60%"
  },
  {
    "state": "Montana",
    "2016obesrate": "25.50%",
    "2015obesrate": "23.60%",
    "2014obesrate": "26.40%",
    "2013obesrate": "24.60%",
    "2012obesrate": "24.30%"
  },
  {
    "state": "Nebraska",
    "2016obesrate": "32.00%",
    "2015obesrate": "31.40%",
    "2014obesrate": "30.20%",
    "2013obesrate": "29.60%",
    "2012obesrate": "28.60%"
  },
  {
    "state": "Nevada",
    "2016obesrate": "25.80%",
    "2015obesrate": "26.70%",
    "2014obesrate": "27.70%",
    "2013obesrate": "26.20%",
    "2012obesrate": "26.20%"
  },
  {
    "state": "New Hamphire",
    "2016obesrate": "26.60%",
    "2015obesrate": "26.30%",
    "2014obesrate": "27.40%",
    "2013obesrate": "26.70%",
    "2012obesrate": "27.30%"
  },
  {
    "state": "New Jersey",
    "2016obesrate": "27.40%",
    "2015obesrate": "25.60%",
    "2014obesrate": "26.90%",
    "2013obesrate": "26.30%",
    "2012obesrate": "24.60%"
  },
  {
    "state": "New Mexico",
    "2016obesrate": "28.30%",
    "2015obesrate": "28.80%",
    "2014obesrate": "28.40%",
    "2013obesrate": "26.40%",
    "2012obesrate": "27.10%"
  },
  {
    "state": "New York",
    "2016obesrate": "25.50%",
    "2015obesrate": "25.00%",
    "2014obesrate": "27.00%",
    "2013obesrate": "25.40%",
    "2012obesrate": "23.60%"
  },
  {
    "state": "North Carolina",
    "2016obesrate": "31.80%",
    "2015obesrate": "31.00%",
    "2014obesrate": "29.70%",
    "2013obesrate": "29.40%",
    "2012obesrate": "29.60%"
  },
  {
    "state": "North Dakota",
    "2016obesrate": "31.90%",
    "2015obesrate": "31.00%",
    "2014obesrate": "32.20%",
    "2013obesrate": "31.00%",
    "2012obesrate": "29.70%"
  },
  {
    "state": "Ohio",
    "2016obesrate": "31.50%",
    "2015obesrate": "29.80%",
    "2014obesrate": "32.60%",
    "2013obesrate": "30.40%",
    "2012obesrate": "30.10%"
  },
  {
    "state": "Oklahoma",
    "2016obesrate": "32.80%",
    "2015obesrate": "33.90%",
    "2014obesrate": "33.00%",
    "2013obesrate": "32.50%",
    "2012obesrate": "32.20%"
  },
  {
    "state": "Oregon",
    "2016obesrate": "28.70%",
    "2015obesrate": "30.10%",
    "2014obesrate": "27.90%",
    "2013obesrate": "26.50%",
    "2012obesrate": "27.30%"
  },
  {
    "state": "Pennsylvania",
    "2016obesrate": "30.30%",
    "2015obesrate": "30.00%",
    "2014obesrate": "30.20%",
    "2013obesrate": "30.00%",
    "2012obesrate": "29.10%"
  },
  {
    "state": "Rhode Island",
    "2016obesrate": "26.60%",
    "2015obesrate": "26.00%",
    "2014obesrate": "27.00%",
    "2013obesrate": "27.30%",
    "2012obesrate": "25.70%"
  },
  {
    "state": "South Carolina",
    "2016obesrate": "32.30%",
    "2015obesrate": "31.70%",
    "2014obesrate": "32.10%",
    "2013obesrate": "31.70%",
    "2012obesrate": "31.60%"
  },
  {
    "state": "South Dakota",
    "2016obesrate": "29.60%",
    "2015obesrate": "30.40%",
    "2014obesrate": "29.80%",
    "2013obesrate": "29.90%",
    "2012obesrate": "28.10%"
  },
  {
    "state": "Tennessee",
    "2016obesrate": "34.80%",
    "2015obesrate": "33.80%",
    "2014obesrate": "31.20%",
    "2013obesrate": "33.70%",
    "2012obesrate": "31.10%"
  },
  {
    "state": "Texas",
    "2016obesrate": "33.70%",
    "2015obesrate": "32.40%",
    "2014obesrate": "31.90%",
    "2013obesrate": "30.90%",
    "2012obesrate": "29.20%"
  },
  {
    "state": "Utah",
    "2016obesrate": "25.40%",
    "2015obesrate": "24.50%",
    "2014obesrate": "25.70%",
    "2013obesrate": "24.10%",
    "2012obesrate": "24.30%"
  },
  {
    "state": "Vermont",
    "2016obesrate": "27.10%",
    "2015obesrate": "25.10%",
    "2014obesrate": "24.80%",
    "2013obesrate": "24.70%",
    "2012obesrate": "23.70%"
  },
  {
    "state": "Virginia",
    "2016obesrate": "29.00%",
    "2015obesrate": "29.20%",
    "2014obesrate": "28.50%",
    "2013obesrate": "27.20%",
    "2012obesrate": "27.40%"
  },
  {
    "state": "Washington",
    "2016obesrate": "28.60%",
    "2015obesrate": "26.40%",
    "2014obesrate": "27.30%",
    "2013obesrate": "27.20%",
    "2012obesrate": "26.80%"
  },
  {
    "state": "West Virginia",
    "2016obesrate": "37.70%",
    "2015obesrate": "35.60%",
    "2014obesrate": "35.70%",
    "2013obesrate": "35.10%",
    "2012obesrate": "33.80%"
  },
  {
    "state": "Wisconsin",
    "2016obesrate": "30.70%",
    "2015obesrate": "30.70%",
    "2014obesrate": "31.20%",
    "2013obesrate": "29.80%",
    "2012obesrate": "29.70%"
  },
  {
    "state": "Wyoming",
    "2016obesrate": "27.70%",
    "2015obesrate": "29.00%",
    "2014obesrate": "29.50%",
    "2013obesrate": "27.80%",
    "2012obesrate": "24.60%"
  },
  {
    "state": "",
    "2016obesrate": "",
    "2015obesrate": "",
    "2014obesrate": "",
    "2013obesrate": "",
    "2012obesrate": ""
  }
]